dilsorting/__init__.py
dilsorting/bubblesort.py
dilsorting/heapsort.py
dilsorting/insertionsort.py
dilsorting/mergesort.py
dilsorting/quicksort.py
dilsorting/selectionsort.py
dilsorting-1.0.0.dist-info/METADATA
dilsorting-1.0.0.dist-info/WHEEL
dilsorting-1.0.0.dist-info/licenses/LICENSE
dilsorting-1.0.0.dist-info/RECORD
