Metadata-Version: 2.1
Name: dilsorting
Version: 1.0.0
Summary: A python sorting library
Author-email: Diljodh Nahal <diljodhnahal@hotmail.com>
License: Copyright 2022 Diljodh Nahal
Classifier: License :: OSI Approved :: MIT License
Classifier: Operating System :: OS Independent
Classifier: Programming Language :: Python :: 3
Requires-Python: >=3.7
